pyqt_find_path_widget/__init__.py
pyqt_find_path_widget/findPathLineEdit.py
pyqt_find_path_widget/findPathWidget.py
pyqt_find_path_widget/style/__init__.py
pyqt_find_path_widget/style/button.css
pyqt_find_path_widget/style/lineedit.css
pyqt_find_path_widget-0.0.1.dist-info/LICENSE
pyqt_find_path_widget-0.0.1.dist-info/METADATA
pyqt_find_path_widget-0.0.1.dist-info/WHEEL
pyqt_find_path_widget-0.0.1.dist-info/top_level.txt
pyqt_find_path_widget-0.0.1.dist-info/RECORD
