Metadata-Version: 2.1
Name: pyqt-find-path-widget
Version: 0.0.1
Summary: PyQt find path widget (QLabel - QLineEdit - QPushButton)
Home-page: https://github.com/yjg30737/pyqt-find-path-widget.git
Author: Jung Gyu Yoon
Author-email: yjg30737@gmail.com
License: MIT
License-File: LICENSE
Requires-Dist: PyQt5 (>=5.8)
Requires-Dist: pyqt-resource-helper (>=0.0.1)
